browser_cookie4/__init__.py
browser_cookie4/__main__.py
browser_cookie4-0.0.11.dist-info/METADATA
browser_cookie4-0.0.11.dist-info/WHEEL
browser_cookie4-0.0.11.dist-info/entry_points.txt
browser_cookie4-0.0.11.dist-info/top_level.txt
browser_cookie4-0.0.11.dist-info/RECORD
