Metadata-Version: 2.4
Name: browser-cookie4
Version: 0.0.11
Summary: Original author Boris Babic boris.ivan.babic@gmail.com
Home-page: https://github.com/borisbabic/browser_cookie4
Author: Ilya Rakhlin
Author-email: i.rakhlin@gmail.com
Requires-Dist: lz4
Requires-Dist: pycryptodomex
Requires-Dist: urllib3
Requires-Dist: requests
Requires-Dist: websocket-client
Requires-Dist: dbus-python; python_version < "3.7" and ("bsd" in sys_platform or sys_platform == "linux")
Requires-Dist: jeepney; python_version >= "3.7" and ("bsd" in sys_platform or sys_platform == "linux")
Requires-Dist: shadowcopy; python_version >= "3.7" and platform_system == "Windows"
Dynamic: author
Dynamic: author-email
Dynamic: home-page
Dynamic: requires-dist
Dynamic: summary
